nuggetizer/__init__.py
nuggetizer/core/__init__.py
nuggetizer/core/async_llm.py
nuggetizer/core/base.py
nuggetizer/core/llm.py
nuggetizer/core/metrics.py
nuggetizer/core/types.py
nuggetizer/models/__init__.py
nuggetizer/models/async_nuggetizer.py
nuggetizer/models/nuggetizer.py
nuggetizer/utils/__init__.py
nuggetizer/utils/api.py
nuggetizer-0.0.5.dist-info/LICENSE
nuggetizer-0.0.5.dist-info/METADATA
nuggetizer-0.0.5.dist-info/WHEEL
nuggetizer-0.0.5.dist-info/top_level.txt
nuggetizer-0.0.5.dist-info/RECORD
