Metadata-Version: 2.2
Name: nuggetizer
Version: 0.0.5
Summary: A package for Nuggetizer - a tool for information nugget creation and assignment to LLM-generated answers.
Author-email: Ronak Pradeep <rpradeep@uwaterloo.ca>
License:                                  Apache License
Project-URL: Homepage, https://github.com/castorini/nuggetizer
Keywords: Nuggetizer,Fact Recall,LLM,Nuggets,Fact Extraction,RAG Evaluation,Evaluation,RAG
Classifier: Programming Language :: Python
Classifier: Programming Language :: Python :: 3
Provides: nuggetizer
Requires-Python: >=3.10
License-File: LICENSE
Requires-Dist: openai>=1.55.3
Requires-Dist: python-dotenv>=0.19.0
Requires-Dist: typing-extensions>=4.0.0
Requires-Dist: requests>=2.25.0
Requires-Dist: tqdm>=4.65.0
Requires-Dist: tiktoken>=0.8
